gatiab/__init__.py
gatiab/gatiab.py
gatiab-1.1.0.dist-info/LICENSE.txt
gatiab-1.1.0.dist-info/METADATA
gatiab-1.1.0.dist-info/WHEEL
gatiab-1.1.0.dist-info/top_level.txt
gatiab-1.1.0.dist-info/RECORD
