Metadata-Version: 2.1
Name: gatiab
Version: 1.1.0
Summary: Gasous Absorption Transmissions at Instrument Averaged Bands
Author-email: Mustapha Moulana <mm@hygeos.com>
License: 
Classifier: Development Status :: 5 - Production/Stable
Classifier: License :: Free for non-commercial use
Classifier: Intended Audience :: Science/Research
Classifier: Intended Audience :: Developers
Classifier: Programming Language :: Python
Classifier: Programming Language :: Python :: 3
Classifier: Programming Language :: Python :: 3.10
Classifier: Programming Language :: Python :: 3.11
Classifier: Topic :: Scientific/Engineering
Classifier: Operating System :: POSIX :: Linux
Requires-Python: >=3.9.19
License-File: LICENSE.txt
Requires-Dist: numpy>=1.26.4
Requires-Dist: xarray>=2024.7.0
Requires-Dist: netcdf4>=1.7.1
Requires-Dist: scipy>=1.13.1
Requires-Dist: tqdm>=4.66.5
